{"results":[{"frameId":0,"frameData":"RkFLRV9KUEVHX0JZVEVT","audioData":"RkFLRV9BVURJT19EQVRB","cameraPosition":{"x":0.0,"y":0.0,"z":0.0},"cameraRotation":{"x":0.0,"y":0.0,"z":0.0}},{"frameId":0,"frameData":"RkFLRV9KUEVHX0JZVEVT","audioData":"RkFLRV9BVURJT19EQVRB","cameraPosition":{"x":0.0,"y":0.0,"z":0.0},"cameraRotation":{"x":0.0,"y":0.0,"z":0.0}},{"frameId":0,"frameData":"RkFLRV9KUEVHX0JZVEVT","audioData":"RkFLRV9BVURJT19EQVRB","cameraPosition":{"x":0.0,"y":0.0,"z":0.0},"cameraRotation":{"x":0.0,"y":0.0,"z":0.0}},{"frameId":0,"frameData":"RkFLRV9KUEVHX0JZVEVT","audioData":"RkFLRV9BVURJT19EQVRB","cameraPosition":{"x":0.0,"y":0.0,"z":0.0},"cameraRotation":{"x":0.0,"y":0.0,"z":0.0}},{"frameId":0,"frameData":"RkFLRV9KUEVHX0JZVEVT","audioData":"RkFLRV9BVURJT19EQVRB","cameraPosition":{"x":0.0,"y":0.0,"z":0.0},"cameraRotation":{"x":0.0,"y":0.0,"z":0.0}}]}