[
  {
    "frame_id": 0,
    "timestamp": 0.0,
    "detections": {
      "ball": [],
      "stumps": [
        {
          "bbox": [
            920,
            488,
            29,
            145
          ],
          "confidence": 1.0,
          "top": [
            934,
            488
          ],
          "bottom": [
            934,
            633
          ],
          "z": 7.34
        },
        {
          "bbox": [
            941,
            339,
            76,
            316
          ],
          "confidence": 1.0,
          "top": [
            979,
            339
          ],
          "bottom": [
            979,
            655
          ],
          "z": 3.37
        },
        {
          "bbox": [
            924,
            336,
            15,
            104
          ],
          "confidence": 1.0,
          "top": [
            931,
            336
          ],
          "bottom": [
            931,
            440
          ],
          "z": 10.24
        }
      ],
      "batsman": []
    }
  },
  {
    "frame_id": 1,
    "timestamp": 0.03333333333333333,
    "detections": {
      "ball": [],
      "stumps": [
        {
          "bbox": [
            922,
            488,
            28,
            143
          ],
          "confidence": 1.0,
          "top": [
            936,
            488
          ],
          "bottom": [
            936,
            631
          ],
          "z": 7.45
        },
        {
          "bbox": [
            943,
            339,
            77,
            316
          ],
          "confidence": 1.0,
          "top": [
            981,
            339
          ],
          "bottom": [
            981,
            655
          ],
          "z": 3.37
        },
        {
          "bbox": [
            926,
            335,
            18,
            112
          ],
          "confidence": 1.0,
          "top": [
            935,
            335
          ],
          "bottom": [
            935,
            447
          ],
          "z": 9.51
        }
      ],
      "batsman": []
    }
  },
  {
    "frame_id": 2,
    "timestamp": 0.06666666666666667,
    "detections": {
      "ball": [],
      "stumps": [
        {
          "bbox": [
            918,
            487,
            35,
            144
          ],
          "confidence": 1.0,
          "top": [
            935,
            487
          ],
          "bottom": [
            935,
            631
          ],
          "z": 7.4
        },
        {
          "bbox": [
            945,
            338,
            76,
            316
          ],
          "confidence": 1.0,
          "top": [
            983,
            338
          ],
          "bottom": [
            983,
            654
          ],
          "z": 3.37
        },
        {
          "bbox": [
            928,
            335,
            15,
            107
          ],
          "confidence": 1.0,
          "top": [
            935,
            335
          ],
          "bottom": [
            935,
            442
          ],
          "z": 9.95
        }
      ],
      "batsman": []
    }
  },
  {
    "frame_id": 3,
    "timestamp": 0.1,
    "detections": {
      "ball": [],
      "stumps": [
        {
          "bbox": [
            926,
            486,
            29,
            146
          ],
          "confidence": 1.0,
          "top": [
            940,
            486
          ],
          "bottom": [
            940,
            632
          ],
          "z": 7.29
        },
        {
          "bbox": [
            948,
            338,
            76,
            315
          ],
          "confidence": 1.0,
          "top": [
            986,
            338
          ],
          "bottom": [
            986,
            653
          ],
          "z": 3.38
        },
        {
          "bbox": [
            931,
            335,
            15,
            110
          ],
          "confidence": 1.0,
          "top": [
            938,
            335
          ],
          "bottom": [
            938,
            445
          ],
          "z": 9.68
        }
      ],
      "batsman": []
    }
  },
  {
    "frame_id": 4,
    "timestamp": 0.13333333333333333,
    "detections": {
      "ball": [],
      "stumps": [
        {
          "bbox": [
            930,
            486,
            28,
            145
          ],
          "confidence": 1.0,
          "top": [
            944,
            486
          ],
          "bottom": [
            944,
            631
          ],
          "z": 7.34
        },
        {
          "bbox": [
            951,
            338,
            76,
            315
          ],
          "confidence": 1.0,
          "top": [
            989,
            338
          ],
          "bottom": [
            989,
            653
          ],
          "z": 3.38
        },
        {
          "bbox": [
            934,
            337,
            15,
            107
          ],
          "confidence": 1.0,
          "top": [
            941,
            337
          ],
          "bottom": [
            941,
            444
          ],
          "z": 9.95
        }
      ],
      "batsman": []
    }
  },
  {
    "frame_id": 5,
    "timestamp": 0.16666666666666669,
    "detections": {
      "ball": [],
      "stumps": [
        {
          "bbox": [
            936,
            553,
            25,
            78
          ],
          "confidence": 1.0,
          "top": [
            948,
            553
          ],
          "bottom": [
            948,
            631
          ],
          "z": 13.65
        },
        {
          "bbox": [
            954,
            337,
            76,
            315
          ],
          "confidence": 1.0,
          "top": [
            992,
            337
          ],
          "bottom": [
            992,
            652
          ],
          "z": 3.38
        },
        {
          "bbox": [
            937,
            335,
            15,
            109
          ],
          "confidence": 1.0,
          "top": [
            944,
            335
          ],
          "bottom": [
            944,
            444
          ],
          "z": 9.77
        }
      ],
      "batsman": []
    }
  },
  {
    "frame_id": 6,
    "timestamp": 0.2,
    "detections": {
      "ball": [],
      "stumps": [
        {
          "bbox": [
            936,
            485,
            28,
            147
          ],
          "confidence": 1.0,
          "top": [
            950,
            485
          ],
          "bottom": [
            950,
            632
          ],
          "z": 7.24
        },
        {
          "bbox": [
            957,
            337,
            76,
            315
          ],
          "confidence": 1.0,
          "top": [
            995,
            337
          ],
          "bottom": [
            995,
            652
          ],
          "z": 3.38
        },
        {
          "bbox": [
            941,
            336,
            14,
            107
          ],
          "confidence": 1.0,
          "top": [
            948,
            336
          ],
          "bottom": [
            948,
            443
          ],
          "z": 9.95
        }
      ],
      "batsman": []
    }
  },
  {
    "frame_id": 7,
    "timestamp": 0.23333333333333334,
    "detections": {
      "ball": [],
      "stumps": [
        {
          "bbox": [
            939,
            485,
            27,
            147
          ],
          "confidence": 1.0,
          "top": [
            952,
            485
          ],
          "bottom": [
            952,
            632
          ],
          "z": 7.24
        },
        {
          "bbox": [
            959,
            336,
            76,
            315
          ],
          "confidence": 1.0,
          "top": [
            997,
            336
          ],
          "bottom": [
            997,
            651
          ],
          "z": 3.38
        },
        {
          "bbox": [
            943,
            334,
            14,
            107
          ],
          "confidence": 1.0,
          "top": [
            950,
            334
          ],
          "bottom": [
            950,
            441
          ],
          "z": 9.95
        }
      ],
      "batsman": []
    }
  },
  {
    "frame_id": 8,
    "timestamp": 0.26666666666666666,
    "detections": {
      "ball": [],
      "stumps": [
        {
          "bbox": [
            940,
            484,
            28,
            148
          ],
          "confidence": 1.0,
          "top": [
            954,
            484
          ],
          "bottom": [
            954,
            632
          ],
          "z": 7.2
        },
        {
          "bbox": [
            960,
            335,
            77,
            315
          ],
          "confidence": 1.0,
          "top": [
            998,
            335
          ],
          "bottom": [
            998,
            650
          ],
          "z": 3.38
        },
        {
          "bbox": [
            944,
            335,
            15,
            105
          ],
          "confidence": 1.0,
          "top": [
            951,
            335
          ],
          "bottom": [
            951,
            440
          ],
          "z": 10.14
        }
      ],
      "batsman": []
    }
  },
  {
    "frame_id": 9,
    "timestamp": 0.3,
    "detections": {
      "ball": [],
      "stumps": [
        {
          "bbox": [
            942,
            484,
            29,
            147
          ],
          "confidence": 1.0,
          "top": [
            956,
            484
          ],
          "bottom": [
            956,
            631
          ],
          "z": 7.24
        },
        {
          "bbox": [
            963,
            335,
            76,
            314
          ],
          "confidence": 1.0,
          "top": [
            1001,
            335
          ],
          "bottom": [
            1001,
            649
          ],
          "z": 3.39
        },
        {
          "bbox": [
            946,
            334,
            15,
            107
          ],
          "confidence": 1.0,
          "top": [
            953,
            334
          ],
          "bottom": [
            953,
            441
          ],
          "z": 9.95
        }
      ],
      "batsman": []
    }
  },
  {
    "frame_id": 10,
    "timestamp": 0.33333333333333337,
    "detections": {
      "ball": [],
      "stumps": [
        {
          "bbox": [
            948,
            549,
            25,
            83
          ],
          "confidence": 1.0,
          "top": [
            960,
            549
          ],
          "bottom": [
            960,
            632
          ],
          "z": 12.83
        },
        {
          "bbox": [
            965,
            335,
            77,
            315
          ],
          "confidence": 1.0,
          "top": [
            1003,
            335
          ],
          "bottom": [
            1003,
            650
          ],
          "z": 3.38
        },
        {
          "bbox": [
            949,
            332,
            15,
            107
          ],
          "confidence": 1.0,
          "top": [
            956,
            332
          ],
          "bottom": [
            956,
            439
          ],
          "z": 9.95
        }
      ],
      "batsman": []
    }
  },
  {
    "frame_id": 11,
    "timestamp": 0.3666666666666667,
    "detections": {
      "ball": [],
      "stumps": [
        {
          "bbox": [
            975,
            334,
            69,
            315
          ],
          "confidence": 1.0,
          "top": [
            1009,
            334
          ],
          "bottom": [
            1009,
            649
          ],
          "z": 3.38
        },
        {
          "bbox": [
            951,
            331,
            15,
            106
          ],
          "confidence": 1.0,
          "top": [
            958,
            331
          ],
          "bottom": [
            958,
            437
          ],
          "z": 10.05
        }
      ],
      "batsman": []
    }
  },
  {
    "frame_id": 12,
    "timestamp": 0.4,
    "detections": {
      "ball": [],
      "stumps": [
        {
          "bbox": [
            950,
            549,
            25,
            81
          ],
          "confidence": 1.0,
          "top": [
            962,
            549
          ],
          "bottom": [
            962,
            630
          ],
          "z": 13.15
        },
        {
          "bbox": [
            967,
            333,
            78,
            314
          ],
          "confidence": 1.0,
          "top": [
            1006,
            333
          ],
          "bottom": [
            1006,
            647
          ],
          "z": 3.39
        },
        {
          "bbox": [
            951,
            329,
            15,
            107
          ],
          "confidence": 1.0,
          "top": [
            958,
            329
          ],
          "bottom": [
            958,
            436
          ],
          "z": 9.95
        }
      ],
      "batsman": []
    }
  },
  {
    "frame_id": 13,
    "timestamp": 0.43333333333333335,
    "detections": {
      "ball": [],
      "stumps": [
        {
          "bbox": [
            952,
            548,
            23,
            79
          ],
          "confidence": 1.0,
          "top": [
            963,
            548
          ],
          "bottom": [
            963,
            627
          ],
          "z": 13.48
        },
        {
          "bbox": [
            968,
            332,
            77,
            314
          ],
          "confidence": 1.0,
          "top": [
            1006,
            332
          ],
          "bottom": [
            1006,
            646
          ],
          "z": 3.39
        },
        {
          "bbox": [
            952,
            328,
            15,
            108
          ],
          "confidence": 1.0,
          "top": [
            959,
            328
          ],
          "bottom": [
            959,
            436
          ],
          "z": 9.86
        }
      ],
      "batsman": []
    }
  },
  {
    "frame_id": 14,
    "timestamp": 0.4666666666666667,
    "detections": {
      "ball": [],
      "stumps": [
        {
          "bbox": [
            969,
            331,
            78,
            314
          ],
          "confidence": 1.0,
          "top": [
            1008,
            331
          ],
          "bottom": [
            1008,
            645
          ],
          "z": 3.39
        },
        {
          "bbox": [
            954,
            327,
            14,
            109
          ],
          "confidence": 1.0,
          "top": [
            961,
            327
          ],
          "bottom": [
            961,
            436
          ],
          "z": 9.77
        }
      ],
      "batsman": []
    }
  },
  {
    "frame_id": 15,
    "timestamp": 0.5,
    "detections": {
      "ball": [],
      "stumps": [
        {
          "bbox": [
            952,
            546,
            24,
            79
          ],
          "confidence": 1.0,
          "top": [
            964,
            546
          ],
          "bottom": [
            964,
            625
          ],
          "z": 13.48
        },
        {
          "bbox": [
            977,
            329,
            70,
            315
          ],
          "confidence": 1.0,
          "top": [
            1012,
            329
          ],
          "bottom": [
            1012,
            644
          ],
          "z": 3.38
        },
        {
          "bbox": [
            954,
            325,
            14,
            110
          ],
          "confidence": 1.0,
          "top": [
            961,
            325
          ],
          "bottom": [
            961,
            435
          ],
          "z": 9.68
        }
      ],
      "batsman": []
    }
  },
  {
    "frame_id": 16,
    "timestamp": 0.5333333333333333,
    "detections": {
      "ball": [],
      "stumps": [
        {
          "bbox": [
            953,
            543,
            23,
            80
          ],
          "confidence": 1.0,
          "top": [
            964,
            543
          ],
          "bottom": [
            964,
            623
          ],
          "z": 13.31
        },
        {
          "bbox": [
            968,
            325,
            79,
            316
          ],
          "confidence": 1.0,
          "top": [
            1007,
            325
          ],
          "bottom": [
            1007,
            641
          ],
          "z": 3.37
        },
        {
          "bbox": [
            953,
            325,
            15,
            104
          ],
          "confidence": 1.0,
          "top": [
            960,
            325
          ],
          "bottom": [
            960,
            429
          ],
          "z": 10.24
        }
      ],
      "batsman": []
    }
  },
  {
    "frame_id": 17,
    "timestamp": 0.5666666666666667,
    "detections": {
      "ball": [],
      "stumps": [
        {
          "bbox": [
            953,
            541,
            23,
            79
          ],
          "confidence": 1.0,
          "top": [
            964,
            541
          ],
          "bottom": [
            964,
            620
          ],
          "z": 13.48
        },
        {
          "bbox": [
            969,
            324,
            78,
            315
          ],
          "confidence": 1.0,
          "top": [
            1008,
            324
          ],
          "bottom": [
            1008,
            639
          ],
          "z": 3.38
        },
        {
          "bbox": [
            954,
            322,
            15,
            107
          ],
          "confidence": 1.0,
          "top": [
            961,
            322
          ],
          "bottom": [
            961,
            429
          ],
          "z": 9.95
        }
      ],
      "batsman": []
    }
  },
  {
    "frame_id": 18,
    "timestamp": 0.6,
    "detections": {
      "ball": [],
      "stumps": [
        {
          "bbox": [
            954,
            321,
            97,
            316
          ],
          "confidence": 1.0,
          "top": [
            1002,
            321
          ],
          "bottom": [
            1002,
            637
          ],
          "z": 3.37
        },
        {
          "bbox": [
            956,
            318,
            14,
            109
          ],
          "confidence": 1.0,
          "top": [
            963,
            318
          ],
          "bottom": [
            963,
            427
          ],
          "z": 9.77
        }
      ],
      "batsman": []
    }
  },
  {
    "frame_id": 19,
    "timestamp": 0.6333333333333334,
    "detections": {
      "ball": [],
      "stumps": [
        {
          "bbox": [
            1041,
            411,
            9,
            85
          ],
          "confidence": 1.0,
          "top": [
            1045,
            411
          ],
          "bottom": [
            1045,
            496
          ],
          "z": 12.53
        },
        {
          "bbox": [
            954,
            317,
            93,
            316
          ],
          "confidence": 1.0,
          "top": [
            1000,
            317
          ],
          "bottom": [
            1000,
            633
          ],
          "z": 3.37
        },
        {
          "bbox": [
            956,
            315,
            13,
            105
          ],
          "confidence": 1.0,
          "top": [
            962,
            315
          ],
          "bottom": [
            962,
            420
          ],
          "z": 10.14
        }
      ],
      "batsman": []
    }
  },
  {
    "frame_id": 20,
    "timestamp": 0.6666666666666667,
    "detections": {
      "ball": [],
      "stumps": [
        {
          "bbox": [
            1005,
            410,
            12,
            77
          ],
          "confidence": 1.0,
          "top": [
            1011,
            410
          ],
          "bottom": [
            1011,
            487
          ],
          "z": 13.83
        },
        {
          "bbox": [
            1041,
            398,
            8,
            88
          ],
          "confidence": 1.0,
          "top": [
            1045,
            398
          ],
          "bottom": [
            1045,
            486
          ],
          "z": 12.1
        },
        {
          "bbox": [
            996,
            324,
            50,
            306
          ],
          "confidence": 1.0,
          "top": [
            1021,
            324
          ],
          "bottom": [
            1021,
            630
          ],
          "z": 3.48
        },
        {
          "bbox": [
            973,
            315,
            41,
            282
          ],
          "confidence": 1.0,
          "top": [
            993,
            315
          ],
          "bottom": [
            993,
            597
          ],
          "z": 3.78
        },
        {
          "bbox": [
            955,
            314,
            13,
            106
          ],
          "confidence": 1.0,
          "top": [
            961,
            314
          ],
          "bottom": [
            961,
            420
          ],
          "z": 10.05
        }
      ],
      "batsman": []
    }
  },
  {
    "frame_id": 21,
    "timestamp": 0.7000000000000001,
    "detections": {
      "ball": [],
      "stumps": [
        {
          "bbox": [
            952,
            312,
            95,
            315
          ],
          "confidence": 1.0,
          "top": [
            999,
            312
          ],
          "bottom": [
            999,
            627
          ],
          "z": 3.38
        },
        {
          "bbox": [
            955,
            308,
            14,
            108
          ],
          "confidence": 1.0,
          "top": [
            962,
            308
          ],
          "bottom": [
            962,
            416
          ],
          "z": 9.86
        }
      ],
      "batsman": []
    }
  },
  {
    "frame_id": 22,
    "timestamp": 0.7333333333333334,
    "detections": {
      "ball": [],
      "stumps": [
        {
          "bbox": [
            968,
            308,
            78,
            317
          ],
          "confidence": 1.0,
          "top": [
            1007,
            308
          ],
          "bottom": [
            1007,
            625
          ],
          "z": 3.36
        },
        {
          "bbox": [
            954,
            307,
            14,
            104
          ],
          "confidence": 1.0,
          "top": [
            961,
            307
          ],
          "bottom": [
            961,
            411
          ],
          "z": 10.24
        }
      ],
      "batsman": []
    }
  },
  {
    "frame_id": 23,
    "timestamp": 0.7666666666666667,
    "detections": {
      "ball": [],
      "stumps": [
        {
          "bbox": [
            951,
            523,
            22,
            79
          ],
          "confidence": 1.0,
          "top": [
            962,
            523
          ],
          "bottom": [
            962,
            602
          ],
          "z": 13.48
        },
        {
          "bbox": [
            967,
            307,
            78,
            316
          ],
          "confidence": 1.0,
          "top": [
            1006,
            307
          ],
          "bottom": [
            1006,
            623
          ],
          "z": 3.37
        },
        {
          "bbox": [
            953,
            305,
            14,
            102
          ],
          "confidence": 1.0,
          "top": [
            960,
            305
          ],
          "bottom": [
            960,
            407
          ],
          "z": 10.44
        }
      ],
      "batsman": []
    }
  },
  {
    "frame_id": 24,
    "timestamp": 0.8,
    "detections": {
      "ball": [],
      "stumps": [
        {
          "bbox": [
            950,
            519,
            22,
            78
          ],
          "confidence": 1.0,
          "top": [
            961,
            519
          ],
          "bottom": [
            961,
            597
          ],
          "z": 13.65
        },
        {
          "bbox": [
            966,
            304,
            79,
            316
          ],
          "confidence": 1.0,
          "top": [
            1005,
            304
          ],
          "bottom": [
            1005,
            620
          ],
          "z": 3.37
        },
        {
          "bbox": [
            953,
            300,
            14,
            107
          ],
          "confidence": 1.0,
          "top": [
            960,
            300
          ],
          "bottom": [
            960,
            407
          ],
          "z": 9.95
        }
      ],
      "batsman": []
    }
  },
  {
    "frame_id": 25,
    "timestamp": 0.8333333333333334,
    "detections": {
      "ball": [],
      "stumps": [
        {
          "bbox": [
            1001,
            400,
            13,
            87
          ],
          "confidence": 1.0,
          "top": [
            1007,
            400
          ],
          "bottom": [
            1007,
            487
          ],
          "z": 12.24
        },
        {
          "bbox": [
            1037,
            396,
            7,
            78
          ],
          "confidence": 1.0,
          "top": [
            1040,
            396
          ],
          "bottom": [
            1040,
            474
          ],
          "z": 13.65
        },
        {
          "bbox": [
            948,
            302,
            94,
            318
          ],
          "confidence": 1.0,
          "top": [
            995,
            302
          ],
          "bottom": [
            995,
            620
          ],
          "z": 3.35
        },
        {
          "bbox": [
            952,
            299,
            14,
            107
          ],
          "confidence": 1.0,
          "top": [
            959,
            299
          ],
          "bottom": [
            959,
            406
          ],
          "z": 9.95
        }
      ],
      "batsman": []
    }
  },
  {
    "frame_id": 26,
    "timestamp": 0.8666666666666667,
    "detections": {
      "ball": [],
      "stumps": [
        {
          "bbox": [
            1038,
            396,
            7,
            79
          ],
          "confidence": 1.0,
          "top": [
            1041,
            396
          ],
          "bottom": [
            1041,
            475
          ],
          "z": 13.48
        },
        {
          "bbox": [
            969,
            305,
            74,
            316
          ],
          "confidence": 1.0,
          "top": [
            1006,
            305
          ],
          "bottom": [
            1006,
            621
          ],
          "z": 3.37
        },
        {
          "bbox": [
            953,
            302,
            14,
            102
          ],
          "confidence": 1.0,
          "top": [
            960,
            302
          ],
          "bottom": [
            960,
            404
          ],
          "z": 10.44
        }
      ],
      "batsman": []
    }
  },
  {
    "frame_id": 27,
    "timestamp": 0.9,
    "detections": {
      "ball": [
        {
          "bbox": [
            1000,
            -5,
            27,
            27
          ],
          "confidence": 1.0,
          "center": [
            1014,
            8
          ],
          "radius": 13,
          "z": 3.94
        }
      ],
      "stumps": [
        {
          "bbox": [
            943,
            302,
            94,
            318
          ],
          "confidence": 1.0,
          "top": [
            990,
            302
          ],
          "bottom": [
            990,
            620
          ],
          "z": 3.35
        }
      ],
      "batsman": []
    }
  },
  {
    "frame_id": 28,
    "timestamp": 0.9333333333333333,
    "detections": {
      "ball": [],
      "stumps": [
        {
          "bbox": [
            945,
            308,
            96,
            312
          ],
          "confidence": 1.0,
          "top": [
            993,
            308
          ],
          "bottom": [
            993,
            620
          ],
          "z": 3.41
        }
      ],
      "batsman": []
    }
  },
  {
    "frame_id": 29,
    "timestamp": 0.9666666666666667,
    "detections": {
      "ball": [],
      "stumps": [
        {
          "bbox": [
            944,
            314,
            98,
            299
          ],
          "confidence": 1.0,
          "top": [
            993,
            314
          ],
          "bottom": [
            993,
            613
          ],
          "z": 3.56
        },
        {
          "bbox": [
            984,
            307,
            31,
            164
          ],
          "confidence": 1.0,
          "top": [
            999,
            307
          ],
          "bottom": [
            999,
            471
          ],
          "z": 6.49
        }
      ],
      "batsman": []
    }
  },
  {
    "frame_id": 30,
    "timestamp": 1.0,
    "detections": {
      "ball": [],
      "stumps": [
        {
          "bbox": [
            1030,
            397,
            26,
            81
          ],
          "confidence": 1.0,
          "top": [
            1043,
            397
          ],
          "bottom": [
            1043,
            478
          ],
          "z": 13.15
        },
        {
          "bbox": [
            938,
            301,
            88,
            328
          ],
          "confidence": 1.0,
          "top": [
            982,
            301
          ],
          "bottom": [
            982,
            629
          ],
          "z": 3.25
        }
      ],
      "batsman": []
    }
  },
  {
    "frame_id": 31,
    "timestamp": 1.0333333333333334,
    "detections": {
      "ball": [],
      "stumps": [
        {
          "bbox": [
            984,
            314,
            30,
            151
          ],
          "confidence": 1.0,
          "top": [
            999,
            314
          ],
          "bottom": [
            999,
            465
          ],
          "z": 7.05
        }
      ],
      "batsman": []
    }
  },
  {
    "frame_id": 32,
    "timestamp": 1.0665666666666667,
    "detections": {
      "ball": [
        {
          "bbox": [
            1001,
            171,
            25,
            25
          ],
          "confidence": 1.0,
          "center": [
            1014,
            184
          ],
          "radius": 12,
          "z": 4.37
        }
      ],
      "stumps": [],
      "batsman": []
    }
  },
  {
    "frame_id": 33,
    "timestamp": 1.0998,
    "detections": {
      "ball": [],
      "stumps": [],
      "batsman": []
    }
  },
  {
    "frame_id": 34,
    "timestamp": 1.1332333333333333,
    "detections": {
      "ball": [],
      "stumps": [
        {
          "bbox": [
            976,
            456,
            29,
            94
          ],
          "confidence": 1.0,
          "top": [
            990,
            456
          ],
          "bottom": [
            990,
            550
          ],
          "z": 11.33
        }
      ],
      "batsman": []
    }
  },
  {
    "frame_id": 35,
    "timestamp": 1.1665666666666668,
    "detections": {
      "ball": [],
      "stumps": [],
      "batsman": []
    }
  },
  {
    "frame_id": 36,
    "timestamp": 1.1999,
    "detections": {
      "ball": [],
      "stumps": [],
      "batsman": []
    }
  },
  {
    "frame_id": 37,
    "timestamp": 1.2332333333333334,
    "detections": {
      "ball": [
        {
          "bbox": [
            858,
            161,
            31,
            31
          ],
          "confidence": 1.0,
          "center": [
            874,
            177
          ],
          "radius": 15,
          "z": 3.43
        }
      ],
      "stumps": [],
      "batsman": []
    }
  },
  {
    "frame_id": 38,
    "timestamp": 1.2665666666666666,
    "detections": {
      "ball": [],
      "stumps": [],
      "batsman": []
    }
  },
  {
    "frame_id": 39,
    "timestamp": 1.2999,
    "detections": {
      "ball": [],
      "stumps": [
        {
          "bbox": [
            860,
            375,
            55,
            210
          ],
          "confidence": 1.0,
          "top": [
            887,
            375
          ],
          "bottom": [
            887,
            585
          ],
          "z": 5.07
        }
      ],
      "batsman": []
    }
  },
  {
    "frame_id": 40,
    "timestamp": 1.3332333333333335,
    "detections": {
      "ball": [],
      "stumps": [
        {
          "bbox": [
            863,
            373,
            53,
            211
          ],
          "confidence": 1.0,
          "top": [
            889,
            373
          ],
          "bottom": [
            889,
            584
          ],
          "z": 5.05
        }
      ],
      "batsman": []
    }
  },
  {
    "frame_id": 41,
    "timestamp": 1.3665666666666667,
    "detections": {
      "ball": [],
      "stumps": [
        {
          "bbox": [
            865,
            373,
            52,
            212
          ],
          "confidence": 1.0,
          "top": [
            891,
            373
          ],
          "bottom": [
            891,
            585
          ],
          "z": 5.02
        }
      ],
      "batsman": []
    }
  },
  {
    "frame_id": 42,
    "timestamp": 1.3999000000000001,
    "detections": {
      "ball": [],
      "stumps": [
        {
          "bbox": [
            867,
            372,
            48,
            214
          ],
          "confidence": 1.0,
          "top": [
            891,
            372
          ],
          "bottom": [
            891,
            586
          ],
          "z": 4.98
        }
      ],
      "batsman": []
    }
  },
  {
    "frame_id": 43,
    "timestamp": 1.4332333333333334,
    "detections": {
      "ball": [],
      "stumps": [
        {
          "bbox": [
            982,
            457,
            23,
            87
          ],
          "confidence": 1.0,
          "top": [
            993,
            457
          ],
          "bottom": [
            993,
            544
          ],
          "z": 12.24
        },
        {
          "bbox": [
            890,
            375,
            102,
            315
          ],
          "confidence": 1.0,
          "top": [
            941,
            375
          ],
          "bottom": [
            941,
            690
          ],
          "z": 3.38
        },
        {
          "bbox": [
            868,
            371,
            48,
            216
          ],
          "confidence": 1.0,
          "top": [
            892,
            371
          ],
          "bottom": [
            892,
            587
          ],
          "z": 4.93
        }
      ],
      "batsman": []
    }
  },
  {
    "frame_id": 44,
    "timestamp": 1.4665666666666668,
    "detections": {
      "ball": [],
      "stumps": [
        {
          "bbox": [
            891,
            373,
            102,
            316
          ],
          "confidence": 1.0,
          "top": [
            942,
            373
          ],
          "bottom": [
            942,
            689
          ],
          "z": 3.37
        },
        {
          "bbox": [
            870,
            369,
            48,
            216
          ],
          "confidence": 1.0,
          "top": [
            894,
            369
          ],
          "bottom": [
            894,
            585
          ],
          "z": 4.93
        }
      ],
      "batsman": []
    }
  },
  {
    "frame_id": 45,
    "timestamp": 1.4999,
    "detections": {
      "ball": [],
      "stumps": [
        {
          "bbox": [
            893,
            564,
            23,
            110
          ],
          "confidence": 1.0,
          "top": [
            904,
            564
          ],
          "bottom": [
            904,
            674
          ],
          "z": 9.68
        },
        {
          "bbox": [
            911,
            373,
            85,
            322
          ],
          "confidence": 1.0,
          "top": [
            953,
            373
          ],
          "bottom": [
            953,
            695
          ],
          "z": 3.31
        },
        {
          "bbox": [
            871,
            368,
            47,
            216
          ],
          "confidence": 1.0,
          "top": [
            894,
            368
          ],
          "bottom": [
            894,
            584
          ],
          "z": 4.93
        }
      ],
      "batsman": []
    }
  },
  {
    "frame_id": 46,
    "timestamp": 1.5332333333333334,
    "detections": {
      "ball": [],
      "stumps": [
        {
          "bbox": [
            892,
            577,
            24,
            98
          ],
          "confidence": 1.0,
          "top": [
            904,
            577
          ],
          "bottom": [
            904,
            675
          ],
          "z": 10.87
        },
        {
          "bbox": [
            912,
            374,
            85,
            320
          ],
          "confidence": 1.0,
          "top": [
            954,
            374
          ],
          "bottom": [
            954,
            694
          ],
          "z": 3.33
        },
        {
          "bbox": [
            889,
            372,
            30,
            214
          ],
          "confidence": 1.0,
          "top": [
            904,
            372
          ],
          "bottom": [
            904,
            586
          ],
          "z": 4.98
        }
      ],
      "batsman": []
    }
  },
  {
    "frame_id": 47,
    "timestamp": 1.5665666666666667,
    "detections": {
      "ball": [],
      "stumps": [
        {
          "bbox": [
            891,
            588,
            23,
            87
          ],
          "confidence": 1.0,
          "top": [
            902,
            588
          ],
          "bottom": [
            902,
            675
          ],
          "z": 12.24
        },
        {
          "bbox": [
            923,
            374,
            73,
            320
          ],
          "confidence": 1.0,
          "top": [
            959,
            374
          ],
          "bottom": [
            959,
            694
          ],
          "z": 3.33
        },
        {
          "bbox": [
            889,
            368,
            30,
            218
          ],
          "confidence": 1.0,
          "top": [
            904,
            368
          ],
          "bottom": [
            904,
            586
          ],
          "z": 4.89
        }
      ],
      "batsman": []
    }
  },
  {
    "frame_id": 48,
    "timestamp": 1.5999,
    "detections": {
      "ball": [
        {
          "bbox": [
            843,
            -4,
            26,
            26
          ],
          "confidence": 1.0,
          "center": [
            857,
            9
          ],
          "radius": 13,
          "z": 4.07
        }
      ],
      "stumps": [
        {
          "bbox": [
            899,
            368,
            21,
            138
          ],
          "confidence": 1.0,
          "top": [
            909,
            368
          ],
          "bottom": [
            909,
            506
          ],
          "z": 7.72
        }
      ],
      "batsman": []
    }
  },
  {
    "frame_id": 49,
    "timestamp": 1.6332333333333333,
    "detections": {
      "ball": [],
      "stumps": [
        {
          "bbox": [
            898,
            445,
            16,
            84
          ],
          "confidence": 1.0,
          "top": [
            906,
            445
          ],
          "bottom": [
            906,
            529
          ],
          "z": 12.68
        }
      ],
      "batsman": []
    }
  },
  {
    "frame_id": 50,
    "timestamp": 1.6665666666666668,
    "detections": {
      "ball": [],
      "stumps": [
        {
          "bbox": [
            889,
            375,
            103,
            319
          ],
          "confidence": 1.0,
          "top": [
            940,
            375
          ],
          "bottom": [
            940,
            694
          ],
          "z": 3.34
        },
        {
          "bbox": [
            894,
            371,
            22,
            158
          ],
          "confidence": 1.0,
          "top": [
            905,
            371
          ],
          "bottom": [
            905,
            529
          ],
          "z": 6.74
        }
      ],
      "batsman": []
    }
  },
  {
    "frame_id": 51,
    "timestamp": 1.6999000000000002,
    "detections": {
      "ball": [],
      "stumps": [
        {
          "bbox": [
            892,
            372,
            22,
            158
          ],
          "confidence": 1.0,
          "top": [
            903,
            372
          ],
          "bottom": [
            903,
            530
          ],
          "z": 6.74
        }
      ],
      "batsman": []
    }
  },
  {
    "frame_id": 52,
    "timestamp": 1.7332333333333334,
    "detections": {
      "ball": [],
      "stumps": [
        {
          "bbox": [
            979,
            474,
            22,
            79
          ],
          "confidence": 1.0,
          "top": [
            990,
            474
          ],
          "bottom": [
            990,
            553
          ],
          "z": 13.48
        },
        {
          "bbox": [
            892,
            373,
            21,
            158
          ],
          "confidence": 1.0,
          "top": [
            902,
            373
          ],
          "bottom": [
            902,
            531
          ],
          "z": 6.74
        }
      ],
      "batsman": []
    }
  },
  {
    "frame_id": 53,
    "timestamp": 1.7665666666666668,
    "detections": {
      "ball": [
        {
          "bbox": [
            866,
            94,
            28,
            28
          ],
          "confidence": 1.0,
          "center": [
            881,
            108
          ],
          "radius": 14,
          "z": 3.81
        }
      ],
      "stumps": [
        {
          "bbox": [
            881,
            373,
            31,
            214
          ],
          "confidence": 1.0,
          "top": [
            896,
            373
          ],
          "bottom": [
            896,
            587
          ],
          "z": 4.98
        }
      ],
      "batsman": []
    }
  },
  {
    "frame_id": 54,
    "timestamp": 1.7999,
    "detections": {
      "ball": [],
      "stumps": [
        {
          "bbox": [
            883,
            573,
            23,
            101
          ],
          "confidence": 1.0,
          "top": [
            894,
            573
          ],
          "bottom": [
            894,
            674
          ],
          "z": 10.54
        },
        {
          "bbox": [
            903,
            378,
            86,
            311
          ],
          "confidence": 1.0,
          "top": [
            946,
            378
          ],
          "bottom": [
            946,
            689
          ],
          "z": 3.42
        },
        {
          "bbox": [
            882,
            375,
            29,
            170
          ],
          "confidence": 1.0,
          "top": [
            896,
            375
          ],
          "bottom": [
            896,
            545
          ],
          "z": 6.26
        }
      ],
      "batsman": []
    }
  },
  {
    "frame_id": 55,
    "timestamp": 1.8332333333333335,
    "detections": {
      "ball": [
        {
          "bbox": [
            117,
            1059,
            23,
            23
          ],
          "confidence": 1.0,
          "center": [
            129,
            1070
          ],
          "radius": 11,
          "z": 4.69
        }
      ],
      "stumps": [
        {
          "bbox": [
            888,
            373,
            23,
            156
          ],
          "confidence": 1.0,
          "top": [
            899,
            373
          ],
          "bottom": [
            899,
            529
          ],
          "z": 6.83
        }
      ],
      "batsman": []
    }
  },
  {
    "frame_id": 56,
    "timestamp": 1.8665666666666667,
    "detections": {
      "ball": [
        {
          "bbox": [
            117,
            1058,
            23,
            23
          ],
          "confidence": 1.0,
          "center": [
            129,
            1070
          ],
          "radius": 11,
          "z": 4.69
        }
      ],
      "stumps": [
        {
          "bbox": [
            880,
            372,
            30,
            177
          ],
          "confidence": 1.0,
          "top": [
            895,
            372
          ],
          "bottom": [
            895,
            549
          ],
          "z": 6.02
        }
      ],
      "batsman": []
    }
  },
  {
    "frame_id": 57,
    "timestamp": 1.8999000000000001,
    "detections": {
      "ball": [
        {
          "bbox": [
            116,
            1057,
            24,
            24
          ],
          "confidence": 1.0,
          "center": [
            128,
            1070
          ],
          "radius": 12,
          "z": 4.42
        }
      ],
      "stumps": [
        {
          "bbox": [
            902,
            377,
            86,
            312
          ],
          "confidence": 1.0,
          "top": [
            945,
            377
          ],
          "bottom": [
            945,
            689
          ],
          "z": 3.41
        },
        {
          "bbox": [
            887,
            373,
            21,
            157
          ],
          "confidence": 1.0,
          "top": [
            897,
            373
          ],
          "bottom": [
            897,
            530
          ],
          "z": 6.78
        }
      ],
      "batsman": []
    }
  },
  {
    "frame_id": 58,
    "timestamp": 1.9332333333333334,
    "detections": {
      "ball": [
        {
          "bbox": [
            116,
            1057,
            24,
            24
          ],
          "confidence": 1.0,
          "center": [
            128,
            1070
          ],
          "radius": 12,
          "z": 4.42
        }
      ],
      "stumps": [
        {
          "bbox": [
            881,
            548,
            24,
            127
          ],
          "confidence": 1.0,
          "top": [
            893,
            548
          ],
          "bottom": [
            893,
            675
          ],
          "z": 8.39
        },
        {
          "bbox": [
            910,
            377,
            77,
            310
          ],
          "confidence": 1.0,
          "top": [
            948,
            377
          ],
          "bottom": [
            948,
            687
          ],
          "z": 3.44
        },
        {
          "bbox": [
            882,
            371,
            27,
            171
          ],
          "confidence": 1.0,
          "top": [
            895,
            371
          ],
          "bottom": [
            895,
            542
          ],
          "z": 6.23
        }
      ],
      "batsman": []
    }
  },
  {
    "frame_id": 59,
    "timestamp": 1.9665666666666668,
    "detections": {
      "ball": [
        {
          "bbox": [
            861,
            91,
            29,
            29
          ],
          "confidence": 1.0,
          "center": [
            876,
            106
          ],
          "radius": 14,
          "z": 3.71
        }
      ],
      "stumps": [
        {
          "bbox": [
            880,
            523,
            23,
            152
          ],
          "confidence": 1.0,
          "top": [
            891,
            523
          ],
          "bottom": [
            891,
            675
          ],
          "z": 7.01
        },
        {
          "bbox": [
            912,
            377,
            75,
            311
          ],
          "confidence": 1.0,
          "top": [
            949,
            377
          ],
          "bottom": [
            949,
            688
          ],
          "z": 3.42
        },
        {
          "bbox": [
            887,
            372,
            21,
            155
          ],
          "confidence": 1.0,
          "top": [
            897,
            372
          ],
          "bottom": [
            897,
            527
          ],
          "z": 6.87
        }
      ],
      "batsman": []
    }
  },
  {
    "frame_id": 60,
    "timestamp": 1.9999,
    "detections": {
      "ball": [],
      "stumps": [
        {
          "bbox": [
            977,
            456,
            15,
            80
          ],
          "confidence": 1.0,
          "top": [
            984,
            456
          ],
          "bottom": [
            984,
            536
          ],
          "z": 13.31
        },
        {
          "bbox": [
            889,
            377,
            18,
            123
          ],
          "confidence": 1.0,
          "top": [
            898,
            377
          ],
          "bottom": [
            898,
            500
          ],
          "z": 8.66
        },
        {
          "bbox": [
            881,
            376,
            105,
            316
          ],
          "confidence": 1.0,
          "top": [
            933,
            376
          ],
          "bottom": [
            933,
            692
          ],
          "z": 3.37
        }
      ],
      "batsman": []
    }
  },
  {
    "frame_id": 61,
    "timestamp": 2.0332333333333334,
    "detections": {
      "ball": [
        {
          "bbox": [
            863,
            97,
            25,
            25
          ],
          "confidence": 1.0,
          "center": [
            876,
            110
          ],
          "radius": 12,
          "z": 4.25
        }
      ],
      "stumps": [
        {
          "bbox": [
            976,
            455,
            14,
            85
          ],
          "confidence": 1.0,
          "top": [
            983,
            455
          ],
          "bottom": [
            983,
            540
          ],
          "z": 12.53
        },
        {
          "bbox": [
            888,
            376,
            18,
            127
          ],
          "confidence": 1.0,
          "top": [
            897,
            376
          ],
          "bottom": [
            897,
            503
          ],
          "z": 8.39
        }
      ],
      "batsman": []
    }
  },
  {
    "frame_id": 62,
    "timestamp": 2.0665666666666667,
    "detections": {
      "ball": [],
      "stumps": [
        {
          "bbox": [
            974,
            457,
            12,
            83
          ],
          "confidence": 1.0,
          "top": [
            980,
            457
          ],
          "bottom": [
            980,
            540
          ],
          "z": 12.83
        },
        {
          "bbox": [
            880,
            376,
            104,
            315
          ],
          "confidence": 1.0,
          "top": [
            932,
            376
          ],
          "bottom": [
            932,
            691
          ],
          "z": 3.38
        },
        {
          "bbox": [
            888,
            376,
            18,
            123
          ],
          "confidence": 1.0,
          "top": [
            897,
            376
          ],
          "bottom": [
            897,
            499
          ],
          "z": 8.66
        }
      ],
      "batsman": []
    }
  },
  {
    "frame_id": 63,
    "timestamp": 2.0999000000000008,
    "detections": {
      "ball": [
        {
          "bbox": [
            466,
            405,
            23,
            23
          ],
          "confidence": 1.0,
          "center": [
            478,
            417
          ],
          "radius": 11,
          "z": 4.67
        }
      ],
      "stumps": [
        {
          "bbox": [
            973,
            454,
            13,
            88
          ],
          "confidence": 1.0,
          "top": [
            979,
            454
          ],
          "bottom": [
            979,
            542
          ],
          "z": 12.1
        },
        {
          "bbox": [
            887,
            375,
            18,
            124
          ],
          "confidence": 1.0,
          "top": [
            896,
            375
          ],
          "bottom": [
            896,
            499
          ],
          "z": 8.59
        }
      ],
      "batsman": []
    }
  },
  {
    "frame_id": 64,
    "timestamp": 2.1332333333333335,
    "detections": {
      "ball": [
        {
          "bbox": [
            464,
            402,
            23,
            23
          ],
          "confidence": 1.0,
          "center": [
            476,
            414
          ],
          "radius": 11,
          "z": 4.62
        }
      ],
      "stumps": [
        {
          "bbox": [
            969,
            457,
            15,
            90
          ],
          "confidence": 1.0,
          "top": [
            976,
            457
          ],
          "bottom": [
            976,
            547
          ],
          "z": 11.83
        },
        {
          "bbox": [
            885,
            376,
            18,
            123
          ],
          "confidence": 1.0,
          "top": [
            894,
            376
          ],
          "bottom": [
            894,
            499
          ],
          "z": 8.66
        }
      ],
      "batsman": []
    }
  },
  {
    "frame_id": 65,
    "timestamp": 2.1665666666666668,
    "detections": {
      "ball": [
        {
          "bbox": [
            854,
            97,
            28,
            28
          ],
          "confidence": 1.0,
          "center": [
            868,
            112
          ],
          "radius": 14,
          "z": 3.91
        }
      ],
      "stumps": [
        {
          "bbox": [
            967,
            456,
            17,
            87
          ],
          "confidence": 1.0,
          "top": [
            975,
            456
          ],
          "bottom": [
            975,
            543
          ],
          "z": 12.24
        },
        {
          "bbox": [
            874,
            376,
            104,
            315
          ],
          "confidence": 1.0,
          "top": [
            926,
            376
          ],
          "bottom": [
            926,
            691
          ],
          "z": 3.38
        },
        {
          "bbox": [
            881,
            376,
            19,
            123
          ],
          "confidence": 1.0,
          "top": [
            890,
            376
          ],
          "bottom": [
            890,
            499
          ],
          "z": 8.66
        }
      ],
      "batsman": []
    }
  },
  {
    "frame_id": 66,
    "timestamp": 2.1998,
    "detections": {
      "ball": [],
      "stumps": [
        {
          "bbox": [
            964,
            455,
            15,
            87
          ],
          "confidence": 1.0,
          "top": [
            971,
            455
          ],
          "bottom": [
            971,
            542
          ],
          "z": 12.24
        },
        {
          "bbox": [
            875,
            375,
            22,
            139
          ],
          "confidence": 1.0,
          "top": [
            886,
            375
          ],
          "bottom": [
            886,
            514
          ],
          "z": 7.66
        }
      ],
      "batsman": []
    }
  },
  {
    "frame_id": 67,
    "timestamp": 2.2330333333333336,
    "detections": {
      "ball": [],
      "stumps": [
        {
          "bbox": [
            955,
            475,
            21,
            117
          ],
          "confidence": 1.0,
          "top": [
            965,
            475
          ],
          "bottom": [
            965,
            592
          ],
          "z": 9.1
        },
        {
          "bbox": [
            874,
            427,
            14,
            78
          ],
          "confidence": 1.0,
          "top": [
            881,
            427
          ],
          "bottom": [
            881,
            505
          ],
          "z": 13.65
        }
      ],
      "batsman": []
    }
  },
  {
    "frame_id": 68,
    "timestamp": 2.2664666666666666,
    "detections": {
      "ball": [
        {
          "bbox": [
            1105,
            334,
            25,
            25
          ],
          "confidence": 1.0,
          "center": [
            1118,
            346
          ],
          "radius": 12,
          "z": 4.29
        }
      ],
      "stumps": [
        {
          "bbox": [
            949,
            478,
            20,
            115
          ],
          "confidence": 1.0,
          "top": [
            959,
            478
          ],
          "bottom": [
            959,
            593
          ],
          "z": 9.26
        },
        {
          "bbox": [
            868,
            376,
            20,
            130
          ],
          "confidence": 1.0,
          "top": [
            878,
            376
          ],
          "bottom": [
            878,
            506
          ],
          "z": 8.19
        }
      ],
      "batsman": []
    }
  },
  {
    "frame_id": 69,
    "timestamp": 2.2998000000000003,
    "detections": {
      "ball": [
        {
          "bbox": [
            1193,
            359,
            24,
            24
          ],
          "confidence": 1.0,
          "center": [
            1205,
            372
          ],
          "radius": 12,
          "z": 4.42
        }
      ],
      "stumps": [
        {
          "bbox": [
            941,
            478,
            18,
            115
          ],
          "confidence": 1.0,
          "top": [
            950,
            478
          ],
          "bottom": [
            950,
            593
          ],
          "z": 9.26
        },
        {
          "bbox": [
            860,
            376,
            20,
            129
          ],
          "confidence": 1.0,
          "top": [
            870,
            376
          ],
          "bottom": [
            870,
            505
          ],
          "z": 8.26
        }
      ],
      "batsman": []
    }
  },
  {
    "frame_id": 70,
    "timestamp": 2.3331333333333335,
    "detections": {
      "ball": [],
      "stumps": [
        {
          "bbox": [
            929,
            479,
            21,
            115
          ],
          "confidence": 1.0,
          "top": [
            939,
            479
          ],
          "bottom": [
            939,
            594
          ],
          "z": 9.26
        },
        {
          "bbox": [
            849,
            375,
            21,
            133
          ],
          "confidence": 1.0,
          "top": [
            859,
            375
          ],
          "bottom": [
            859,
            508
          ],
          "z": 8.01
        }
      ],
      "batsman": []
    }
  },
  {
    "frame_id": 71,
    "timestamp": 2.3664666666666667,
    "detections": {
      "ball": [],
      "stumps": [
        {
          "bbox": [
            838,
            429,
            16,
            89
          ],
          "confidence": 1.0,
          "top": [
            846,
            429
          ],
          "bottom": [
            846,
            518
          ],
          "z": 11.97
        }
      ],
      "batsman": []
    }
  },
  {
    "frame_id": 72,
    "timestamp": 2.3998,
    "detections": {
      "ball": [],
      "stumps": [],
      "batsman": []
    }
  },
  {
    "frame_id": 73,
    "timestamp": 2.4331333333333336,
    "detections": {
      "ball": [],
      "stumps": [
        {
          "bbox": [
            791,
            377,
            40,
            185
          ],
          "confidence": 1.0,
          "top": [
            811,
            377
          ],
          "bottom": [
            811,
            562
          ],
          "z": 5.76
        }
      ],
      "batsman": []
    }
  },
  {
    "frame_id": 74,
    "timestamp": 2.466466666666667,
    "detections": {
      "ball": [
        {
          "bbox": [
            40,
            827,
            22,
            22
          ],
          "confidence": 1.0,
          "center": [
            51,
            838
          ],
          "radius": 11,
          "z": 4.87
        }
      ],
      "stumps": [
        {
          "bbox": [
            766,
            376,
            49,
            186
          ],
          "confidence": 1.0,
          "top": [
            790,
            376
          ],
          "bottom": [
            790,
            562
          ],
          "z": 5.73
        }
      ],
      "batsman": []
    }
  },
  {
    "frame_id": 75,
    "timestamp": 2.4998,
    "detections": {
      "ball": [],
      "stumps": [
        {
          "bbox": [
            751,
            376,
            46,
            187
          ],
          "confidence": 1.0,
          "top": [
            774,
            376
          ],
          "bottom": [
            774,
            563
          ],
          "z": 5.7
        }
      ],
      "batsman": []
    }
  },
  {
    "frame_id": 76,
    "timestamp": 2.5331333333333332,
    "detections": {
      "ball": [],
      "stumps": [
        {
          "bbox": [
            752,
            374,
            27,
            153
          ],
          "confidence": 1.0,
          "top": [
            765,
            374
          ],
          "bottom": [
            765,
            527
          ],
          "z": 6.96
        }
      ],
      "batsman": []
    }
  },
  {
    "frame_id": 77,
    "timestamp": 2.566466666666667,
    "detections": {
      "ball": [],
      "stumps": [],
      "batsman": []
    }
  },
  {
    "frame_id": 78,
    "timestamp": 2.5998,
    "detections": {
      "ball": [],
      "stumps": [],
      "batsman": []
    }
  },
  {
    "frame_id": 79,
    "timestamp": 2.6331333333333333,
    "detections": {
      "ball": [],
      "stumps": [
        {
          "bbox": [
            709,
            412,
            20,
            89
          ],
          "confidence": 1.0,
          "top": [
            719,
            412
          ],
          "bottom": [
            719,
            501
          ],
          "z": 11.97
        }
      ],
      "batsman": []
    }
  },
  {
    "frame_id": 80,
    "timestamp": 2.666466666666667,
    "detections": {
      "ball": [],
      "stumps": [
        {
          "bbox": [
            698,
            369,
            27,
            132
          ],
          "confidence": 1.0,
          "top": [
            711,
            369
          ],
          "bottom": [
            711,
            501
          ],
          "z": 8.07
        }
      ],
      "batsman": []
    }
  },
  {
    "frame_id": 81,
    "timestamp": 2.6998,
    "detections": {
      "ball": [],
      "stumps": [
        {
          "bbox": [
            774,
            463,
            17,
            77
          ],
          "confidence": 1.0,
          "top": [
            782,
            463
          ],
          "bottom": [
            782,
            540
          ],
          "z": 13.83
        },
        {
          "bbox": [
            696,
            368,
            22,
            99
          ],
          "confidence": 1.0,
          "top": [
            707,
            368
          ],
          "bottom": [
            707,
            467
          ],
          "z": 10.76
        }
      ],
      "batsman": []
    }
  },
  {
    "frame_id": 82,
    "timestamp": 2.7331333333333334,
    "detections": {
      "ball": [],
      "stumps": [
        {
          "bbox": [
            767,
            463,
            18,
            80
          ],
          "confidence": 1.0,
          "top": [
            776,
            463
          ],
          "bottom": [
            776,
            543
          ],
          "z": 13.31
        },
        {
          "bbox": [
            690,
            368,
            23,
            98
          ],
          "confidence": 1.0,
          "top": [
            701,
            368
          ],
          "bottom": [
            701,
            466
          ],
          "z": 10.87
        }
      ],
      "batsman": []
    }
  },
  {
    "frame_id": 83,
    "timestamp": 2.7664666666666666,
    "detections": {
      "ball": [],
      "stumps": [
        {
          "bbox": [
            762,
            463,
            18,
            79
          ],
          "confidence": 1.0,
          "top": [
            771,
            463
          ],
          "bottom": [
            771,
            542
          ],
          "z": 13.48
        },
        {
          "bbox": [
            685,
            366,
            23,
            98
          ],
          "confidence": 1.0,
          "top": [
            696,
            366
          ],
          "bottom": [
            696,
            464
          ],
          "z": 10.87
        }
      ],
      "batsman": []
    }
  },
  {
    "frame_id": 84,
    "timestamp": 2.7897555555555558,
    "detections": {
      "ball": [],
      "stumps": [],
      "batsman": []
    }
  },
  {
    "frame_id": 85,
    "timestamp": 2.823088888888889,
    "detections": {
      "ball": [
        {
          "bbox": [
            1105,
            117,
            26,
            26
          ],
          "confidence": 1.0,
          "center": [
            1118,
            131
          ],
          "radius": 13,
          "z": 4.07
        }
      ],
      "stumps": [
        {
          "bbox": [
            670,
            362,
            44,
            146
          ],
          "confidence": 1.0,
          "top": [
            692,
            362
          ],
          "bottom": [
            692,
            508
          ],
          "z": 7.29
        }
      ],
      "batsman": []
    }
  },
  {
    "frame_id": 86,
    "timestamp": 2.856422222222222,
    "detections": {
      "ball": [],
      "stumps": [
        {
          "bbox": [
            668,
            361,
            43,
            147
          ],
          "confidence": 1.0,
          "top": [
            689,
            361
          ],
          "bottom": [
            689,
            508
          ],
          "z": 7.24
        }
      ],
      "batsman": []
    }
  },
  {
    "frame_id": 87,
    "timestamp": 2.889755555555556,
    "detections": {
      "ball": [],
      "stumps": [],
      "batsman": []
    }
  },
  {
    "frame_id": 88,
    "timestamp": 2.923088888888889,
    "detections": {
      "ball": [],
      "stumps": [
        {
          "bbox": [
            671,
            361,
            38,
            129
          ],
          "confidence": 1.0,
          "top": [
            690,
            361
          ],
          "bottom": [
            690,
            490
          ],
          "z": 8.26
        }
      ],
      "batsman": []
    }
  },
  {
    "frame_id": 89,
    "timestamp": 2.9564222222222223,
    "detections": {
      "ball": [],
      "stumps": [
        {
          "bbox": [
            670,
            361,
            27,
            129
          ],
          "confidence": 1.0,
          "top": [
            683,
            361
          ],
          "bottom": [
            683,
            490
          ],
          "z": 8.26
        }
      ],
      "batsman": []
    }
  },
  {
    "frame_id": 90,
    "timestamp": 2.9897555555555555,
    "detections": {
      "ball": [
        {
          "bbox": [
            1243,
            466,
            24,
            24
          ],
          "confidence": 1.0,
          "center": [
            1256,
            478
          ],
          "radius": 12,
          "z": 4.41
        }
      ],
      "stumps": [
        {
          "bbox": [
            674,
            359,
            22,
            98
          ],
          "confidence": 1.0,
          "top": [
            685,
            359
          ],
          "bottom": [
            685,
            457
          ],
          "z": 10.87
        }
      ],
      "batsman": []
    }
  },
  {
    "frame_id": 91,
    "timestamp": 3.023088888888889,
    "detections": {
      "ball": [
        {
          "bbox": [
            858,
            62,
            22,
            22
          ],
          "confidence": 1.0,
          "center": [
            869,
            73
          ],
          "radius": 11,
          "z": 4.97
        }
      ],
      "stumps": [
        {
          "bbox": [
            673,
            357,
            29,
            100
          ],
          "confidence": 1.0,
          "top": [
            687,
            357
          ],
          "bottom": [
            687,
            457
          ],
          "z": 10.65
        }
      ],
      "batsman": []
    }
  },
  {
    "frame_id": 92,
    "timestamp": 3.0564222222222224,
    "detections": {
      "ball": [
        {
          "bbox": [
            860,
            319,
            34,
            34
          ],
          "confidence": 1.0,
          "center": [
            878,
            336
          ],
          "radius": 17,
          "z": 3.2
        }
      ],
      "stumps": [],
      "batsman": []
    }
  },
  {
    "frame_id": 93,
    "timestamp": 3.0897555555555556,
    "detections": {
      "ball": [],
      "stumps": [
        {
          "bbox": [
            660,
            412,
            26,
            113
          ],
          "confidence": 1.0,
          "top": [
            673,
            412
          ],
          "bottom": [
            673,
            525
          ],
          "z": 9.42
        }
      ],
      "batsman": []
    }
  },
  {
    "frame_id": 94,
    "timestamp": 3.1230888888888892,
    "detections": {
      "ball": [],
      "stumps": [
        {
          "bbox": [
            668,
            356,
            39,
            131
          ],
          "confidence": 1.0,
          "top": [
            687,
            356
          ],
          "bottom": [
            687,
            487
          ],
          "z": 8.13
        }
      ],
      "batsman": []
    }
  },
  {
    "frame_id": 95,
    "timestamp": 3.1564222222222225,
    "detections": {
      "ball": [
        {
          "bbox": [
            1187,
            283,
            24,
            24
          ],
          "confidence": 1.0,
          "center": [
            1199,
            296
          ],
          "radius": 12,
          "z": 4.55
        }
      ],
      "stumps": [
        {
          "bbox": [
            669,
            353,
            26,
            116
          ],
          "confidence": 1.0,
          "top": [
            682,
            353
          ],
          "bottom": [
            682,
            469
          ],
          "z": 9.18
        }
      ],
      "batsman": []
    }
  },
  {
    "frame_id": 96,
    "timestamp": 3.1897555555555557,
    "detections": {
      "ball": [
        {
          "bbox": [
            1187,
            281,
            23,
            23
          ],
          "confidence": 1.0,
          "center": [
            1198,
            293
          ],
          "radius": 11,
          "z": 4.68
        }
      ],
      "stumps": [
        {
          "bbox": [
            669,
            350,
            33,
            115
          ],
          "confidence": 1.0,
          "top": [
            685,
            350
          ],
          "bottom": [
            685,
            465
          ],
          "z": 9.26
        }
      ],
      "batsman": []
    }
  }
]